version.py
corva_unit_converter/__init__.py
corva_unit_converter/constants.py
corva_unit_converter/converter.py
corva_unit_converter/helpers.py
corva_unit_converter/definitions/__init__.py
corva_unit_converter/definitions/acoustic_slowness.py
corva_unit_converter/definitions/angle.py
corva_unit_converter/definitions/angle_per_length.py
corva_unit_converter/definitions/angular_velocity.py
corva_unit_converter/definitions/area.py
corva_unit_converter/definitions/current.py
corva_unit_converter/definitions/density.py
corva_unit_converter/definitions/digital.py
corva_unit_converter/definitions/energy.py
corva_unit_converter/definitions/force.py
corva_unit_converter/definitions/gamma_radiation.py
corva_unit_converter/definitions/gas_concentration.py
corva_unit_converter/definitions/gas_volume.py
corva_unit_converter/definitions/inverse_pressure.py
corva_unit_converter/definitions/length.py
corva_unit_converter/definitions/length_per_angle.py
corva_unit_converter/definitions/mass.py
corva_unit_converter/definitions/mass_flow_rate.py
corva_unit_converter/definitions/mpl.py
corva_unit_converter/definitions/parts_per.py
corva_unit_converter/definitions/permiability.py
corva_unit_converter/definitions/porosity.py
corva_unit_converter/definitions/power.py
corva_unit_converter/definitions/pressure.py
corva_unit_converter/definitions/pressure_gradient.py
corva_unit_converter/definitions/proportion.py
corva_unit_converter/definitions/revolution_per_volume.py
corva_unit_converter/definitions/speed.py
corva_unit_converter/definitions/strokes_rate.py
corva_unit_converter/definitions/temperature.py
corva_unit_converter/definitions/time.py
corva_unit_converter/definitions/torque.py
corva_unit_converter/definitions/viscosity.py
corva_unit_converter/definitions/voltage.py
corva_unit_converter/definitions/volume_concentration.py
corva_unit_converter/definitions/volume_flow_rate.py
corva_unit_converter-0.5.0.dist-info/LICENSE.md
corva_unit_converter-0.5.0.dist-info/METADATA
corva_unit_converter-0.5.0.dist-info/WHEEL
corva_unit_converter-0.5.0.dist-info/top_level.txt
corva_unit_converter-0.5.0.dist-info/RECORD
