Metadata-Version: 2.1
Name: corva-unit-converter
Version: 0.5.0
Summary: Unit converter for O&G(and other) units
Home-page: https://github.com/corva-ai/corva-convert-units-py
Author: Yuliya Klimushina
Author-email: yuliya.klimushina@corva.ai
License: MIT
Keywords: corva,unit converter
Classifier: Development Status :: 4 - Beta
Classifier: Intended Audience :: Developers
Classifier: Operating System :: OS Independent
Classifier: Programming Language :: Python
Classifier: Programming Language :: Python :: 3
Classifier: Programming Language :: Python :: 3.8
Classifier: Topic :: Software Development :: Libraries
Requires-Python: >=3.8, <4.0
License-File: LICENSE.md
